vedantsh/__init__.py
vedantsh/__main__.py
vedantsh/terminal.py
vedantsh-1.0.0.dist-info/licenses/LICENSE
vedantsh-1.0.0.dist-info/METADATA
vedantsh-1.0.0.dist-info/WHEEL
vedantsh-1.0.0.dist-info/entry_points.txt
vedantsh-1.0.0.dist-info/top_level.txt
vedantsh-1.0.0.dist-info/RECORD
